[
	{
		"bookshelf": 1029,
		"No": 29,
		"title": "A'dan Z'ye Düşünmek",
		"publisher": "ALFA YAYINLARI",
		"author": "Nigel Warburton",
		"lang": "TÜRKÇE",
		"page": 232,
		"year": "2019",
		"notes": "B-1"
	},
	{
		"bookshelf": 1030,
		"No": 30,
		"title": "A'dan Z'ye Psikoloji",
		"publisher": "SAY YAYINLARI",
		"author": "Lisa J. Cohen",
		"lang": "TÜRKÇE",
		"page": 560,
		"year": "2022",
		"notes": "C-4"
	},
	{
		"bookshelf": 1031,
		"No": 31,
		"title": "Acemi Yoginin Ayurveda Yolculuğu",
		"publisher": "Paloma",
		"author": "Esra E. Karaosmanoğlu",
		"lang": "Turkce",
		"page": 144,
		"year": "2021",
		"notes": "F-4"
	},
	{
		"bookshelf": 1032,
		"No": 32,
		"title": "Acemi Yoginin Elkitabı & Yeni Başlayanlar İçin Yoga",
		"publisher": "PALOMA YAYINLARI",
		"author": "Esra E. Karaosmanoğlu",
		"lang": "TÜRKÇE",
		"page": 224,
		"year": "2017",
		"notes": "E-4"
	},
	{
		"bookshelf": 1033,
		"No": 33,
		"title": "Açık Liderlik & Sosyal Teknoloji Yönetme Tarzınızı Nasıl Değiştirir?",
		"publisher": "OPTİMİST YAYINLARI",
		"author": "Charlene Li",
		"lang": "TÜRKÇE",
		"page": 302,
		"year": "2011",
		"notes": "D-4"
	},
	{
		"bookshelf": 1034,
		"No": 34,
		"title": "Açılın Gençler Geliyor",
		"publisher": "CEO PLUS",
		"author": "Fatoş Karahasan",
		"lang": "TÜRKÇE",
		"page": 200,
		"year": "2018",
		"notes": "E-3"
	},
	{
		"bookshelf": 1035,
		"No": 35,
		"title": "Acımasız Dünyaya Meydan Okumak",
		"publisher": "BUTİK YAYINCILIK",
		"author": "Brene Brown",
		"lang": "TÜRKÇE",
		"page": 168,
		"year": "2018",
		"notes": "B-4"
	},
	{
		"bookshelf": 1036,
		"No": 36,
		"title": "Acısız Bilim & Bilim, Günlük Hayatı Nasıl Değiştiriyor?",
		"publisher": "NTV YAYINLARI",
		"author": "Chris Smith",
		"lang": "TÜRKÇE",
		"page": 304,
		"year": "2015",
		"notes": "B-1"
	},
	{
		"bookshelf": 1037,
		"No": 37,
		"title": "Act’i Kolay Öğrenmek & Kabul ve Kararlılık Terapisi İçin Hızlı Bir Başlangıç",
		"publisher": "LİTERA YAYINCILIK",
		"author": "Russ Harris",
		"lang": "TÜRKÇE",
		"page": 556,
		"year": "2022",
		"notes": "C-3"
	},
	{
		"bookshelf": 1038,
		"No": 38,
		"title": "Afacan Bir Psikanalistin Düşünceleri",
		"publisher": "YAPI KREDİ YAYINLARI",
		"author": "Antonino Ferro",
		"lang": "TÜRKÇE",
		"page": 152,
		"year": "2023",
		"notes": "new"
	},
	{
		"bookshelf": 1039,
		"No": 39,
		"title": "Ağ Toplumu",
		"publisher": "KAFKA KİTAP",
		"author": "Jan van Dijk",
		"lang": "TÜRKÇE",
		"page": 454,
		"year": "2018",
		"notes": "B-1"
	},
	{
		"bookshelf": 1040,
		"No": 40,
		"title": "Akıl",
		"publisher": "AYLAK KİTAP",
		"author": "Richard M. Restak",
		"lang": "TÜRKÇE",
		"page": 216,
		"year": "2016",
		"notes": "E-2"
	},
	{
		"bookshelf": 1041,
		"No": 41,
		"title": "Akıl Sağlıgimızı Nasıl Koruruz",
		"publisher": "SEL YAYINCILIK",
		"author": "Philippa Perry",
		"lang": "TÜRKÇE",
		"page": 128,
		"year": "2013",
		"notes": "C-1"
	},
	{
		"bookshelf": 1042,
		"No": 42,
		"title": "Akıl Virüsü",
		"publisher": "PEGASUS YAYINLARI",
		"author": "Richard Brodie",
		"lang": "TÜRKÇE",
		"page": 288,
		"year": "2014",
		"notes": "A-3"
	},
	{
		"bookshelf": 1043,
		"No": 43,
		"title": "Akılcı İyimser & Refahın Evrimi",
		"publisher": "BOĞAZİÇİ ÜNİVERSİTESİ YAYINEVİ",
		"author": "Matt Ridley",
		"lang": "TÜRKÇE",
		"page": 400,
		"year": "2013",
		"notes": "A-2"
	},
	{
		"bookshelf": 1044,
		"No": 44,
		"title": "Akılcı Yaşam Kılavuzu",
		"publisher": "EKSİ KİTAPLAR",
		"author": "Albert Ellis, Robert A. Harper",
		"lang": "TÜRKÇE",
		"page": 389,
		"year": "2017",
		"notes": "A-3"
	},
	{
		"bookshelf": 1045,
		"No": 45,
		"title": "Akıldışı Ama Öngörülebilir",
		"publisher": "OPTİMİST YAYINLARI",
		"author": "Dan Ariely",
		"lang": "TÜRKÇE",
		"page": 428,
		"year": "2013",
		"notes": "B-4"
	},
	{
		"bookshelf": 1046,
		"No": 46,
		"title": "Akıldışı Sevgilerimle & Kayıp Çoraplar ve Diğer Varoluşsal Muammalar",
		"publisher": "OPTİMİST YAYINLARI",
		"author": "Dan Ariely",
		"lang": "TÜRKÇE",
		"page": 232,
		"year": "2015",
		"notes": "B-4"
	},
	{
		"bookshelf": 1047,
		"No": 47,
		"title": "Akıldışının Mantığı & Evdeki ve İşteki Mantığa Başkaldırmanın Beklenmedik Faydaları",
		"publisher": "OPTİMİST YAYINLARI",
		"author": "Dan Ariely",
		"lang": "TÜRKÇE",
		"page": 293,
		"year": "2014",
		"notes": "B-4"
	},
	{
		"bookshelf": 1048,
		"No": 48,
		"title": "Akılgözü & Bilinçli Farkındalık ve Kendini İyileştiren Beyin",
		"publisher": "DİYOJEN YAYINCILIK",
		"author": "Daniel J. Siegel",
		"lang": "TÜRKÇE",
		"page": 408,
		"year": "2019",
		"notes": "A-3"
	},
	{
		"bookshelf": 1049,
		"No": 49,
		"title": "Akıllı Homo Saphiens",
		"publisher": "SAY YAYINLARI",
		"author": "Leonard Mlodinow",
		"lang": "TÜRKÇE",
		"page": 464,
		"year": "2019",
		"notes": "A-3"
	},
	{
		"bookshelf": 1050,
		"No": 50,
		"title": "Akıllı Makineler &Yapay Zeka Hayatımızı Nasıl Değiştiriyor",
		"publisher": "PALOMA YAYINLARI",
		"author": "Ulrich Eberl",
		"lang": "TÜRKÇE",
		"page": 356,
		"year": "2019",
		"notes": "D-2"
	},
	{
		"bookshelf": 1051,
		"No": 51,
		"title": "Akıntıya Karşı - Bizi Aşağı Çeken Psikolojik Güçler",
		"publisher": "Sola Unitas",
		"author": "Dan Heath",
		"lang": "Turkce",
		"page": 312,
		"year": "2022",
		"notes": "new"
	},
	{
		"bookshelf": 1052,
		"No": 52,
		"title": "Akış: Mutluluk Bilimi",
		"publisher": "BUZDAĞI YAYINLARI",
		"author": "Prof. Dr. Mihaly Csikszentmihalyi",
		"lang": "TÜRKÇE",
		"page": 416,
		"year": "2017",
		"notes": "A-2"
	},
	{
		"bookshelf": 1053,
		"No": 53,
		"title": "Akışkan Gözetim",
		"publisher": "AYRINTI YAYINLARI",
		"author": "Zygmunt Bauman, David Lyon",
		"lang": "TÜRKÇE",
		"page": 176,
		"year": "2016",
		"notes": "C-2"
	},
	{
		"bookshelf": 1054,
		"No": 54,
		"title": "Akışkan Modern Dünyada Kültür",
		"publisher": "ATIF YAYINLARI",
		"author": "Zygmunt Bauman",
		"lang": "TÜRKÇE",
		"page": 132,
		"year": "2015",
		"notes": "C-2"
	},
	{
		"bookshelf": 1055,
		"No": 55,
		"title": "Akışkan Modernite",
		"publisher": "CAN YAYINLARI",
		"author": "Zygmunt Bauman",
		"lang": "TÜRKÇE",
		"page": 312,
		"year": "2017",
		"notes": "C-2"
	},
	{
		"bookshelf": 1056,
		"No": 56,
		"title": "Akla Gelmeyen",
		"publisher": "PEGASUS YAYINLARI",
		"author": "Amanda Ripley",
		"lang": "TÜRKÇE",
		"page": 336,
		"year": "2013",
		"notes": "B-2"
	},
	{
		"bookshelf": 1057,
		"No": 57,
		"title": "Akli Yeniden Kurmak",
		"publisher": "Henkel",
		"author": "Danah Zohar",
		"lang": "Turkce",
		"page": 206,
		"year": "1998",
		"notes": "E-3"
	},
	{
		"bookshelf": 1058,
		"No": 58,
		"title": "Aklımın Aklı: Psikoloji",
		"publisher": "NOBEL YAYIN DAĞITIM",
		"author": "McGraw-Hill",
		"lang": "TÜRKÇE",
		"page": 456,
		"year": "2015",
		"notes": "C-4"
	},
	{
		"bookshelf": 1059,
		"No": 59,
		"title": "Aklın G'özü",
		"publisher": "ALFA YAYINLARI",
		"author": "Daniel C. Dennett, Douglas Hofstadter",
		"lang": "TÜRKÇE",
		"page": 600,
		"year": "2021",
		"notes": "A-2"
	},
	{
		"bookshelf": 1060,
		"No": 60,
		"title": "Aklın Yeni Sınırları",
		"publisher": "MEDİACAT KİTAPLARI",
		"author": "Daniel H. Pink",
		"lang": "TÜRKÇE",
		"page": 300,
		"year": "2011",
		"notes": "E-2"
	},
	{
		"bookshelf": 1061,
		"No": 61,
		"title": "Aklında Kalsın & Başarılı Öğrenme Bilimi",
		"publisher": "BUZDAĞI YAYINLARI",
		"author": "Peter C. Brown, Henry L. Roediger, Mark A. McDaniel",
		"lang": "TÜRKÇE",
		"page": 320,
		"year": "2017",
		"notes": "A-2"
	},
	{
		"bookshelf": 1062,
		"No": 62,
		"title": "Aklını En Doğru Şekilde Kullan",
		"publisher": "YAKAMOZ YAYINCILIK",
		"author": "Dr. Carol S. Dweck",
		"lang": "TÜRKÇE",
		"page": 360,
		"year": "2020",
		"notes": "C-4"
	},
	{
		"bookshelf": 1063,
		"No": 63,
		"title": "Aklını Kullan Aksini Düşün",
		"publisher": "BOYNER YAYINLARI",
		"author": "Paul Arden",
		"lang": "TÜRKÇE",
		"page": 144,
		"year": "2007",
		"notes": "C-1"
	},
	{
		"bookshelf": 1064,
		"No": 64,
		"title": "Aklıselim",
		"publisher": "KETEBE YAYINEVİ",
		"author": "Nicholas Epley",
		"lang": "TÜRKÇE",
		"page": 280,
		"year": "2019",
		"notes": "B-3"
	},
	{
		"bookshelf": 1065,
		"No": 65,
		"title": "Aldatıcı Rastlantısallık & Hayatta ve Piyasalarda Şansın Gizli Rolü",
		"publisher": "VARLIK YAYINLARI",
		"author": "Nassim Nicholas Taleb",
		"lang": "TÜRKÇE",
		"page": 352,
		"year": "2019",
		"notes": "B-4"
	},
	{
		"bookshelf": 1066,
		"No": 66,
		"title": "Aldatma Sanatı",
		"publisher": "ODTÜ GELİŞTİRME VAKFI YAYINCILIK VE İLETİŞİM A.Ş.",
		"author": "William L. Simon, Kevin D. Mitnick",
		"lang": "TÜRKÇE",
		"page": 320,
		"year": "2013",
		"notes": "D-2"
	},
	{
		"bookshelf": 1067,
		"No": 67,
		"title": "Alışkanlıkların Gücü & Özel ve İş Hayatımızda Alışkanlıklarımızın Ardında Ne Yatar?",
		"publisher": "BOYNER HOLDİNG YAYINLARI",
		"author": "Charles Duhigg",
		"lang": "TÜRKÇE",
		"page": 432,
		"year": "2017",
		"notes": "A-1"
	},
	{
		"bookshelf": 1068,
		"No": 68,
		"title": "Alışveriş Merkezleri Nereye Kadar?",
		"publisher": "GÜNIŞIĞI KİTAPLIĞI",
		"author": "Paco Underhill",
		"lang": "TÜRKÇE",
		"page": 223,
		"year": "2005",
		"notes": "D-4"
	},
	{
		"bookshelf": 1069,
		"No": 69,
		"title": "Alışveriş Yapmadığım Yıl",
		"publisher": "BUTİK YAYINCILIK",
		"author": "Cait Flanders",
		"lang": "TÜRKÇE",
		"page": 208,
		"year": "2018",
		"notes": "A-2"
	},
	{
		"bookshelf": 1070,
		"No": 70,
		"title": "Alışverişte Kadın Erkek",
		"publisher": "OPTİMİST YAYINLARI",
		"author": "Elizabeth Pace",
		"lang": "TÜRKÇE",
		"page": 174,
		"year": "2011",
		"notes": "D-4"
	},
	{
		"bookshelf": 1071,
		"No": 71,
		"title": "Almanlar Neden Daha İyi Yapıyor: Gelişmiş Bir Ülkeden Notlar",
		"publisher": "İTHAKİ YAYINLARI",
		"author": "John Kampfner",
		"lang": "TÜRKÇE",
		"page": 312,
		"year": "2022",
		"notes": "D-2"
	},
	{
		"bookshelf": 1072,
		"No": 72,
		"title": "Alternatif Eğitim & Hayatımızın Okulsuzlaştırılması",
		"publisher": "KALKEDON YAYINLARI",
		"author": "Matt Hern",
		"lang": "TÜRKÇE",
		"page": 280,
		"year": "2008",
		"notes": "A-2"
	},
	{
		"bookshelf": 1073,
		"No": 73,
		"title": "Alternatif Medyayı Anlamak",
		"publisher": "KAFKA KİTAP",
		"author": "Olga Guedes Balley, Bart Cammaerts, Nico Carpentier",
		"lang": "TÜRKÇE",
		"page": 280,
		"year": "2015",
		"notes": "B-2"
	},
	{
		"bookshelf": 1074,
		"No": 74,
		"title": "Altın Kemer Efsanesi",
		"publisher": "ROTA YAYINLARI",
		"author": "John F. love",
		"lang": "TÜRKÇE",
		"page": 328,
		"year": "1989",
		"notes": "D-3"
	}
]
